{
  "name": "roles/mapsanalytics.viewer",
  "title": "Maps Analytics Viewer",
  "description": "Grants read-only access to all of the Maps Analytics resources.",
  "included_permissions": [
    "mapsanalytics.metricData.query",
    "mapsanalytics.metricMetadata.list",
    "resourcemanager.projects.get",
    "resourcemanager.projects.list",
    "serviceusage.consumerpolicy.get",
    "serviceusage.effectivepolicy.get",
    "serviceusage.groups.list",
    "serviceusage.groups.listMembers",
    "serviceusage.services.list",
    "serviceusage.values.test"
  ],
  "stage": "BETA"
}